README.md
setup.py
null_object/__init__.py
null_object.egg-info/PKG-INFO
null_object.egg-info/SOURCES.txt
null_object.egg-info/dependency_links.txt
null_object.egg-info/top_level.txt